empiar_depositor/__init__.py
empiar_depositor/empiar_deposition.schema.json
empiar_depositor/empiar_depositor.py
empiar_depositor/tests/__init__.py
empiar_depositor/tests/test_aspera_upload.py
empiar_depositor/tests/test_create_new_deposition.py
empiar_depositor/tests/test_globus_upload.py
empiar_depositor/tests/test_grant_rights.py
empiar_depositor/tests/test_main.py
empiar_depositor/tests/test_make_request.py
empiar_depositor/tests/test_redeposit.py
empiar_depositor/tests/test_submit_deposition.py
empiar_depositor/tests/test_thumbnail_upload.py
empiar_depositor/tests/testutils.py
empiar_depositor/tests/deposition_json/working_example.json
empiar_depositor/tests/img/entry_thumbnail.gif
empiar_depositor-1.6b29.dist-info/LICENSE.txt
empiar_depositor-1.6b29.dist-info/METADATA
empiar_depositor-1.6b29.dist-info/WHEEL
empiar_depositor-1.6b29.dist-info/entry_points.txt
empiar_depositor-1.6b29.dist-info/top_level.txt
empiar_depositor-1.6b29.dist-info/RECORD
