Metadata-Version: 2.1
Name: empiar-depositor
Version: 1.6b29
Summary: Script for depositing the data into EMPIAR using EMPIAR API
Author: Andrii Iudin
Author-email: andrii@ebi.ac.uk, andrii.iudin@gmail.com
License: Apache License
Keywords: EMPIAR,deposition,microscopy
Classifier: Development Status :: 4 - Beta
Classifier: Environment :: Console
Classifier: Intended Audience :: Developers
Classifier: Intended Audience :: Science/Research
Classifier: License :: OSI Approved :: Apache Software License
Classifier: Programming Language :: Python :: 2.7
Classifier: Programming Language :: Python :: 3.7
License-File: LICENSE.txt
Requires-Dist: requests
